[{"judul":"fuse box diagram  u0026gt  bmw 3 e91  e92  e93  2005","link":"https:\/\/fuse-box.info\/wp-content\/uploads\/2018\/07\/BMW-3-Series-E90_E91_E92_E93-2005-2013_in_03-09.jpg","thumb":"https:\/\/tse4.mm.bing.net\/th?id=OIP.vFz6IX-Pt5sDzGM_DcltbAHaED&pid=Api&P=0&w=300&h=300"},{"judul":"1064 bmw e91 fuse diagram","link":"http:\/\/7.indiana-ir1403.changeip.co\/images\/bmw-e91-fuse-diagram-5fe53dc816ef34658630f720ce490d3d.png","thumb":"https:\/\/tse4.mm.bing.net\/th?id=OIP.le-a3t96NFfARqL2RwqHOgHaHa&pid=Api&P=0&w=300&h=300"},{"judul":"fuse  7 in  u0026 39 11 335i e90","link":"http:\/\/www.m3post.com\/forums\/attachment.php?attachmentid=325596u0026stc=1u0026d=1258145256","thumb":"https:\/\/tse3.mm.bing.net\/th?id=OIP.jVIWoNU_E0J_umt-Hx0JYAHaG0&pid=Api&P=0&w=300&h=300"},{"judul":"fuse and relay box diagram bmw e90","link":"https:\/\/fusesdiagram.com\/wp-content\/uploads\/2016\/11\/EN-BMWE90-blokrelay-9.jpg","thumb":"https:\/\/tse1.mm.bing.net\/th?id=OIP.gXm2SIrou5Fr0BfS0gCjdQHaGE&pid=Api&P=0&w=300&h=300"},{"judul":"bmw 3 series  e90  e91  e92  e93   2005 - 2010","link":"https:\/\/www.autogenius.info\/wp-content\/uploads\/2018\/06\/bmw-3-series-e90-e91-e92-e93-fuse-box-diagram-behind-glove-compartment-1.jpg","thumb":"https:\/\/tse1.mm.bing.net\/th?id=OIP.rXdJuAmyBbb1RkddpgeyIwHaGW&pid=Api&P=0&w=300&h=300"},{"judul":"tag for bmw 1 series fuse box diagram   2006 bmw 330i fuse","link":"http:\/\/img.bmwcase.com\/full\/a1a68a68f571cb27-2007-bmw-z4-fuse-box-diagram-further-2007-bmw-335i-fuse.gif","thumb":"https:\/\/tse2.mm.bing.net\/th?id=OIP.UM54XC9ets8frpceHoJLsgHaFv&pid=Api&P=0&w=300&h=300"},{"judul":"bmw e90 fuse diagram","link":"https:\/\/i0.wp.com\/chainimage.com\/images\/2007-bmw-328i-sunroof-fuse-please-help-fuse-diagram.jpg?w%5C%5Cu003d1000","thumb":"https:\/\/tse3.mm.bing.net\/th?id=OIP.64ui6ZqEJy5q-HDmIDy7HAHaJ6&pid=Api&P=0&w=300&h=300"},{"judul":"roger vivi ersaks  april 2018","link":"http:\/\/img.bmwcase.com\/full\/60b776707f1be12c-bmw-1-series-fuse-box-diagram-awesome-e46-fuse-diagram.png","thumb":"https:\/\/tse3.mm.bing.net\/th?id=OIP.9MbJsxmdHJ78Pb4RuVFH9AHaEf&pid=Api&P=0&w=300&h=300"},{"judul":"330i fuse diagram","link":"https:\/\/fusesdiagram.com\/wp-content\/uploads\/2016\/11\/EN-BMWE90-blokrelay-10.jpg","thumb":"https:\/\/tse4.mm.bing.net\/th?id=OIP.grLvEzxn_zPcmbi9SjjIdwHaGI&pid=Api&P=0&w=300&h=300"},{"judul":"2006 bmw 325i fuse box","link":"https:\/\/stickerdeals.net\/wp-content\/uploads\/2017\/05\/help-headlight-fuses-bmw-forum-bimmerwerkz-inside-2006-bmw-325i-fuse-box.jpg","thumb":"https:\/\/tse1.mm.bing.net\/th?id=OIP.0JtVODIsu_JIbPTLoKLhhAHaOO&pid=Api&P=0&w=300&h=300"},{"judul":"2006 bmw 325i fuse box diagram  u2014 untpikapps","link":"https:\/\/www.untpikapps.com\/wp-content\/uploads\/2018\/08\/bmw-x3-motor-wiring-diagram-example-electrical-wiring-diagram-e280a2-2006-bmw-325i-fuse-box-diagram.jpg","thumb":"https:\/\/tse1.mm.bing.net\/th?id=OIP.2vBVI5wZB3GMXurZdo0-uwHaJl&pid=Api&P=0&w=300&h=300"},{"judul":"non","link":"https:\/\/www.e90post.com\/forums\/attachment.php?s=04a72c6f688e995a16664a16e61a6ee1u0026attachmentid=824811u0026stc=1u0026d=1361988774","thumb":"https:\/\/tse2.mm.bing.net\/th?id=OIP.X_Zt366xtx-bFMqhFZEMzgHaIQ&pid=Api&P=0&w=300&h=300"},{"judul":"bmw e93 fuse box","link":"http:\/\/img.bmwcase.com\/full\/53ad4fd370682d97-bmw-e93-fuse-box-diagram-bmw-320d-fuse-box-diagram.jpg","thumb":"https:\/\/tse2.mm.bing.net\/th?id=OIP.t4NVt2YWy9wIH1LxPx9JPgHaFy&pid=Api&P=0&w=300&h=300"},{"judul":"fuse and relay box diagram bmw e90","link":"https:\/\/fusesdiagram.com\/wp-content\/uploads\/2016\/11\/EN-BMWE90-blokrelay-8.jpg","thumb":"https:\/\/tse4.mm.bing.net\/th?id=OIP.lQkHfabZAQJZSc26h5eQSQHaFj&pid=Api&P=0&w=300&h=300"},{"judul":"the cigarette lighter and auxillary power sockets on my","link":"http:\/\/www.justanswer.com\/uploads\/eurotec\/2008-11-29_020141_330fusebox.jpg","thumb":"https:\/\/tse4.mm.bing.net\/th?id=OIP.lUl5Z_mooh6Lu_FkON41rAHaGq&pid=Api&P=0&w=300&h=300"},{"judul":"e90 fuse box guide","link":"https:\/\/lh3.googleusercontent.com\/proxy\/vaV9rKFPM8MOBU0Wi1VGQN5eUdtEdiX_FNbKmeFXvlsigLNPjrBhl6Vd2OLOIJh-xKRHoL1xw3YW6F4o4d41YVRP0Wiy34W45QHv_6pZR0OYpRolY1l7FIi7QPs_ioMJpdOu0kkyJhtfvHdb1Etg-m38=w1200-h630-p-k-no-nu","thumb":"https:\/\/tse3.mm.bing.net\/th?id=OIP.8CnZbUQZEIGe9nS9LuPVDwHaIR&pid=Api&P=0&w=300&h=300"},{"judul":"where is fuse box bmw e90","link":"https:\/\/i.pinimg.com\/originals\/92\/55\/62\/9255626344243ad8ddd95e228802eb59.jpg","thumb":"https:\/\/tse3.mm.bing.net\/th?id=OIP.P3MdtsN6RJqiTWN8TwJXfwHaED&pid=Api&P=0&w=300&h=300"},{"judul":"tag for bmw 1 series fuse diagram   1988 bmw 325i fuse box","link":"http:\/\/img.bmwcase.com\/full\/ddd32c80f132e9be-2008-bmw-335i-sedan-fuse-box-diagram-bmw-wiring-diagrams-instructions.jpg","thumb":"https:\/\/tse1.mm.bing.net\/th?id=OIP.JUcxyMDSoNaF-UQ_B02RDgHaMx&pid=Api&P=0&w=300&h=300"},{"judul":"2006 bmw 325i fuse box diagram  u2014 untpikapps","link":"http:\/\/www.untpikapps.com\/wp-content\/uploads\/2018\/08\/bmw-1-series-fuse-box-diagram-cigarette-lighter-luxury-vauxhall-2006-bmw-325i-fuse-box-diagram.jpg","thumb":"https:\/\/tse1.mm.bing.net\/th?id=OIP.hD1ttV36BgyC-18hSwaGNwHaPs&pid=Api&P=0&w=300&h=300"},{"judul":"fuse box diagramme","link":"http:\/\/www.m3post.com\/forums\/attachment.php?attachmentid=325597u0026stc=1u0026d=1258145256","thumb":"https:\/\/tse1.mm.bing.net\/th?id=OIP.U0N8jxVl7JtMa93Xas7tNgHaIF&pid=Api&P=0&w=300&h=300"},{"judul":"bmw e90 e92 e93 fuse box location and fuse diagram 318i","link":"https:\/\/i.ytimg.com\/vi\/b6pfK4zLZOc\/maxresdefault.jpg","thumb":"https:\/\/tse1.mm.bing.net\/th?id=OIP.zjPVg6JRYS64JoaWxfl3cwHaEK&pid=Api&P=0&w=300&h=300"},{"judul":"2008 x5 fuse box diagram help","link":"https:\/\/xoutpost.com\/attachments\/x5-e70-forum\/71855d1496149533-2008-x5-fuse-box-diagram-help-x5-fuse-panelssz.jpg","thumb":"https:\/\/tse3.mm.bing.net\/th?id=OIP.hGQu0pjDl_sMv1tfKSpK6gHaEE&pid=Api&P=0&w=300&h=300"},{"judul":"bmw 3 series fuse box diagram","link":"https:\/\/lh6.googleusercontent.com\/proxy\/yeXkOFaVeXWH2RqGObpdejsm3Mo4jTUZP0CeqtgcTpx6ukkJXv8S_8Y4I3M_hF-iBeOv0mN_Yr6_MFDrnPMN-ijPg9r4EB6LrI6wbS-Fu7ngIYXI4wZaW9b8yjye54_o3Cw3xPKwW9JlKMRC6h2N=w1200-h630-p-k-no-nu","thumb":"https:\/\/tse4.mm.bing.net\/th?id=OIP.Aw8ylF5GlkzEYPUeo1q6-AHaEv&pid=Api&P=0&w=300&h=300"},{"judul":"1997 bmw 328i fuse box location","link":"https:\/\/lh6.googleusercontent.com\/proxy\/1EF_ATd8XP9SULzbATDBc2x7xrSjzh8xR84ADoV6FyDt4zqapvBduYT9lKt0FQb4svLAFgJ3XN0h0kICM0xAFyUQTR1Q6mzBr_3Y5SpkDxwmX8mLEU0NpncjRg=w1200-h630-p-k-no-nu","thumb":"https:\/\/tse1.mm.bing.net\/th?id=OIP.Z-5ZtoByUTznJRDK8cSCkwHaHL&pid=Api&P=0&w=300&h=300"},{"judul":"e46 m3 fuse box","link":"https:\/\/www.bimmerfest.com\/forums\/attachment.php?attachmentid=230887u0026d=1274377501","thumb":"https:\/\/tse3.mm.bing.net\/th?id=OIP.VJsoV9VJ79GuIJQKjjOA_QHaE8&pid=Api&P=0&w=300&h=300"},{"judul":"fuses and relays location bmw 5 series 3 series e90 e39","link":"http:\/\/i.ytimg.com\/vi\/wH7tdv6Rarc\/maxresdefault.jpg","thumb":"https:\/\/tse1.mm.bing.net\/th?id=OIP.2NQGS-utE_G5xs2bOw7FgQHaEK&pid=Api&P=0&w=300&h=300"},{"judul":"bmw e90 central locking wiring diagram","link":"https:\/\/lh6.googleusercontent.com\/proxy\/pTlIdzijtPA-uUoddmpzCo09QYXi7iwxJWFzKcZP2_8LCyChQnCW0yfjeBAWWDrp7gyr2pw1IvSK1Lxv3vx_czNq335F8PyXezjgZqAjvaFw4Q=w1200-h630-p-k-no-nu","thumb":"https:\/\/tse3.mm.bing.net\/th?id=OIP.-5JF32z6RiZj18p5kObISAHaEe&pid=Api&P=0&w=300&h=300"},{"judul":"fuse box location and diagrams  bmw 3 e91  e92","link":"https:\/\/i.ytimg.com\/vi\/svOG0aLrkvs\/maxresdefault.jpg","thumb":"https:\/\/tse2.mm.bing.net\/th?id=OIP.-WxWCH3vHCztipckmVJUjQHaEK&pid=Api&P=0&w=300&h=300"},{"judul":"bmw e91 fuse diagram","link":"https:\/\/lh3.googleusercontent.com\/proxy\/kwnIms0r0QdvcwAq_lnpG0ZlCkx084rfyaY3vlN_-rgUaAhenjTNyjb9hFh8zVOy6B6rGoBWIpy0T0QK3iV9hXxjejGpoIC9f0Z0qaKNgUmHfgo3dMbBjjF-KciGQQ_v2ucKacTuHc5KeZ6Oni4IIeo=s0-d","thumb":"https:\/\/tse1.mm.bing.net\/th?id=OIP.X6b-HOAoDaoYrI68n6mM7QAAAA&pid=Api&P=0&w=300&h=300"},{"judul":"335xi fuse box location","link":"https:\/\/fusesdiagram.com\/wp-content\/uploads\/2016\/11\/EN-BMWE90-blokrelay-7.jpg","thumb":"https:\/\/tse3.mm.bing.net\/th?id=OIP.U6vSePGska3eVxCPrzsS4QHaIq&pid=Api&P=0&w=300&h=300"},{"judul":"35 bmw e90 parts diagram","link":"http:\/\/ills.bmwfans.info\/d6i8.png","thumb":"https:\/\/tse4.mm.bing.net\/th?id=OIP.HUo9JXLsrdcsFEAKd2IQJAHaFL&pid=Api&P=0&w=300&h=300"},{"judul":"bmw e65 e66 fuse box locations with chart diagram","link":"http:\/\/i1.ytimg.com\/vi\/10RU6Ks3aiY\/maxresdefault.jpg","thumb":"https:\/\/tse2.mm.bing.net\/th?id=OIP.Ay8vepoaifWAHEsXNVDURQHaEK&pid=Api&P=0&w=300&h=300"},{"judul":"35 bmw e90 parts diagram","link":"https:\/\/www.diyauto.com\/uploads\/users\/3\/2016\/05\/image01-1464268411.jpg","thumb":"https:\/\/tse2.mm.bing.net\/th?id=OIP.S-mu4LQOmhoa3S1fx0VNGwHaFP&pid=Api&P=0&w=300&h=300"},{"judul":"bmw 3 series e90 wiring diagram","link":"https:\/\/lh6.googleusercontent.com\/proxy\/ihqnBzTgKh5YMjFZBVBuNaSGcM6T1VDFdWpfWo4dkB4u0jGyMwy42PPIClWI0n0ZDXlRHubg4jMLxj0xk-PMa5AUppC95fgcCWjJjzD5DdssYpOgLKvpTZmkox-_snV0COlRKW4Sl6qk4juxl5Z2UR0tOyh2G96VXaBQs4monlB8LPYgkq0o4E0_-U1xTNeKYhLHp3vDknNT5SisAoIdG76YDKzYocBAs8CIKN0AIe-TnVDbSwLj6RFbFJOr5laDl6sVzMP5MRJ4AIRC4hO0uxicpZHUgq45_llMOtDTVY1bJe9AqqE52msGkaqCC2S4jZzY8E6SGlVmSeA=s0-d","thumb":"https:\/\/tse2.mm.bing.net\/th?id=OIP.manl9NVs_uXg8qu8VNH0jgHaG9&pid=Api&P=0&w=300&h=300"},{"judul":"e60 fuse box diagram - e60  e61 2004-2010","link":"http:\/\/forum.bmw5.co.uk\/uploads\/monthly_2017_11\/C.png.b41519025fe24913a57ce8acb6bf3a60.png","thumb":"https:\/\/tse4.mm.bing.net\/th?id=OIP.SJhEtc_O8cGMouJ89ZjsTAHaHa&pid=Api&P=0&w=300&h=300"},{"judul":"95 bmw 740i fuse diagram","link":"https:\/\/lh6.googleusercontent.com\/proxy\/jO-t-Z973gn_6llgDN870AlD3Vw7fcCcEl0UvEuPgqaz9htYk2YWMpaq4U4pTushV_6ptPe75Wo_q3uM9JEuPPxCYWO8uHCDaLNM-kuybwf5XKHJE_EOlChIoIZW=s0-d","thumb":"https:\/\/tse1.mm.bing.net\/th?id=OIP.LER4N-qmIMZBweakkyDYWwHaKo&pid=Api&P=0&w=300&h=300"},{"judul":"where is the alarm fuse","link":"http:\/\/www.e90post.com\/forums\/attachment.php?attachmentid=818459u0026stc=1u0026d=1360545025","thumb":"https:\/\/tse3.mm.bing.net\/th?id=OIP.25Jv8ZSBeDGgKWMaIcN_QwHaIJ&pid=Api&P=0&w=300&h=300"},{"judul":"35 bmw e90 parts diagram","link":"http:\/\/static.bmwfans.info\/images\/epc\/MTUzNjgyX3A=.png","thumb":"https:\/\/tse2.mm.bing.net\/th?id=OIP.RdqY5fwP01vx_7V9WmvaDAHaFP&pid=Api&P=0&w=300&h=300"},{"judul":"m3 fuse box","link":"https:\/\/www.pinclipart.com\/picdir\/middle\/336-3367263_related-with-bmw-e36-m3-fuse-box-lincoln.png","thumb":"https:\/\/tse1.mm.bing.net\/th?id=OIP.7BBuAfe8zhozK-1HxnjMDAHaF7&pid=Api&P=0&w=300&h=300"},{"judul":"35 bmw e90 parts diagram","link":"http:\/\/www.static.estore-central.com\/_diagrame\/mtc3nta5x3a=.jpg","thumb":"https:\/\/tse2.mm.bing.net\/th?id=OIP.mAwK_CMKS6EWznkJDWySLAHaFP&pid=Api&P=0&w=300&h=300"},{"judul":"31 2006 bmw 325i fuse box diagram","link":"https:\/\/lh6.googleusercontent.com\/proxy\/DuHaOgmzKYYu7RsEzO8iWupWRvv4eo7WnukPW7-BuzmYsfSi9I5y8SaGIWU6izhImaIgQxM=w1200-h630-p-k-no-nu","thumb":"https:\/\/tse2.mm.bing.net\/th?id=OIP.phs-soGn3sfxE5Fpy6pECwHaE6&pid=Api&P=0&w=300&h=300"},{"judul":"fuse box for bmw 318i","link":"https:\/\/i.pinimg.com\/originals\/77\/44\/64\/77446405089ae74e668fc4b50c874802.jpg","thumb":"https:\/\/tse1.mm.bing.net\/th?id=OIP.tnKANQ30rORgCNnIlhlD8AHaFr&pid=Api&P=0&w=300&h=300"},{"judul":"bmw 3 series fuse box diagram","link":"https:\/\/fusesdiagram.com\/wp-content\/uploads\/2019\/08\/EN-BMW3F30-blok-kapot-2.jpg","thumb":"https:\/\/tse1.mm.bing.net\/th?id=OIP.e7jCO16O1GdF3MEKuEvVUgHaEz&pid=Api&P=0&w=300&h=300"},{"judul":"95 bmw 740i fuse diagram","link":"https:\/\/images-na.ssl-images-amazon.com\/images\/I\/61gM3KWUE4L._AC_SL1000_.jpg","thumb":"https:\/\/tse2.mm.bing.net\/th?id=OIP.qHM5NCrPdaZA6nbFxIxlKQHaFO&pid=Api&P=0&w=300&h=300"},{"judul":"bmw battery wiring diagram","link":"https:\/\/i0.wp.com\/5series.net\/forums\/attachments\/e61-touring-discussion-4\/150143d1470673568-bmw-e61-hifi-audio-wiring-diagram.jpg","thumb":"https:\/\/tse3.mm.bing.net\/th?id=OIP.REPkikOe9lzggbZkiEE_UwHaJs&pid=Api&P=0&w=300&h=300"},{"judul":"diagram  2000 323i fuse box full version hd quality fuse","link":"http:\/\/www.2040-parts.com\/_content\/items\/images\/57\/1761457\/001.jpg","thumb":"https:\/\/tse2.mm.bing.net\/th?id=OIP.ZD_2y39FHTnXzC-BeoxmCAHaEF&pid=Api&P=0&w=300&h=300"},{"judul":"330i fuse diagram","link":"https:\/\/i2.wp.com\/bimmermodhub.com\/wp-content\/uploads\/2018\/06\/e60-fuse-box-e60e61-2004-2010-bmw-5-series-owners-board-schematic-diagram-of-bmw-e61-fuse-diagram-13899855875144737904.jpg?resize%5C%5C%5C%5C%5C%5C%5C%5C%5C%5C%5C%5C%5C%5C%5C%5C%5C%5C%5C%5C%5C%5C%5C%5C%5C%5C%5C%5C%5C%5C%5C%5C%5C%5C%5C%5C%5C%5C%5C%5C%5C%5C%5C%5C%5C%5C%5C%5C%5C%5C%5C%5C%5C%5C%5C%5C%5C%5C%5C%5C%5C%5C%5C%5Cu003d700%2C619","thumb":"https:\/\/tse4.mm.bing.net\/th?id=OIP.sZs-ZMaOW6w-VrYGEd9_nwHaGj&pid=Api&P=0&w=300&h=300"},{"judul":"1995 bmw 325i fuse box location","link":"https:\/\/deniqueodores.club\/wp-content\/uploads\/2018\/07\/1994-bmw-318i-fuse-box-diagram-trusted-wiring-diagrams-trailer-new-pictures-symbols-terrific-pact-location-of-di.jpg","thumb":"https:\/\/tse1.mm.bing.net\/th?id=OIP.oWpCBqvG3j163uVxaeonWAHaFu&pid=Api&P=0&w=300&h=300"},{"judul":"92 bmw 325i fuse box diagram","link":"https:\/\/i0.wp.com\/stickerdeals.net\/wp-content\/uploads\/2017\/05\/bmw-e36-ac-problems-air-conditioning-318i-323i-325i-328i-with-1995-bmw-318i-fuse-box-diagram.jpg","thumb":"https:\/\/tse4.mm.bing.net\/th?id=OIP.lrQvxbbVfpu0KJLF_gjdZQHaFj&pid=Api&P=0&w=300&h=300"},{"judul":"97 bmw 328i fuse box location","link":"https:\/\/i.ebayimg.com\/images\/g\/16sAAOSwzqtcMV0G\/s-l640.jpg","thumb":"https:\/\/tse2.mm.bing.net\/th?id=OIP.RTOs23nJESSFjtxEgYfOCQHaFZ&pid=Api&P=0&w=300&h=300"}]