[{"judul":"panasonic microwave parts","link":"http:\/\/c.searspartsdirect.com\/lis_png\/PLDM\/50034948-00001.png","thumb":"https:\/\/tse2.mm.bing.net\/th?id=OIP.hhK5-SaJHIMQTBS6vma4jAHaFl&pid=Api&P=0&w=300&h=300"},{"judul":"panasonic microwave parts","link":"http:\/\/c.searspartsdirect.com\/lis_png\/PLDM\/50036268-00001.png","thumb":"https:\/\/tse2.mm.bing.net\/th?id=OIP.S4pZxzARzu7ecqNlgPO2PwHaFn&pid=Api&P=0&w=300&h=300"},{"judul":"panasonic microwave parts","link":"http:\/\/c.searspartsdirect.com\/lis_png\/PLDM\/50019470-00001.png","thumb":"https:\/\/tse1.mm.bing.net\/th?id=OIP.MR34iTszgqP5CoM3HvGCpwHaH5&pid=Api&P=0&w=300&h=300"},{"judul":"panasonic microwave parts","link":"http:\/\/c.searspartsdirect.com\/lis_png\/PLDM\/50029851-00001.png","thumb":"https:\/\/tse3.mm.bing.net\/th?id=OIP.UGhPbcgl5KGq06dfmfJcigHaFQ&pid=Api&P=0&w=300&h=300"},{"judul":"cabinet parts diagram  u0026 parts list for model nnt990sa","link":"http:\/\/c.searspartsdirect.com\/lis_png\/PLDM\/50019993-00001.png","thumb":"https:\/\/tse3.mm.bing.net\/th?id=OIP.cydtqYN25KClkHHVU1Mh4gHaGD&pid=Api&P=0&w=300&h=300"},{"judul":"looking for panasonic model nn","link":"https:\/\/c.searspartsdirect.com\/lis_png\/PLDM\/50020011-00001.png?wid=150u0026hei=150","thumb":"https:\/\/tse4.mm.bing.net\/th?id=OIP.8trAJ9kpToELEnGSEmOI-wHaEy&pid=Api&P=0&w=300&h=300"},{"judul":"panasonic countertop microwave parts","link":"http:\/\/c.searspartsdirect.com\/lis_png\/PLDM\/50026977-00001.png","thumb":"https:\/\/tse3.mm.bing.net\/th?id=OIP.dWBCHGq27y2_PCEcwXfxMwHaFh&pid=Api&P=0&w=300&h=300"},{"judul":"looking for panasonic model nn","link":"https:\/\/c.searspartsdirect.com\/lis_png\/PLDM\/P0104055-00001.png?wid=150u0026hei=150","thumb":"https:\/\/tse3.mm.bing.net\/th?id=OIP.KkkIH8-XvVubh7D5lAs7kAHaFt&pid=Api&P=0&w=300&h=300"},{"judul":"panasonic microwave  convection oven parts","link":"http:\/\/c.searspartsdirect.com\/lis_png\/PLDM\/50019893-00001.png","thumb":"https:\/\/tse3.mm.bing.net\/th?id=OIP.6qyNn73xEFbBqWKCLs6mcAHaFp&pid=Api&P=0&w=300&h=300"},{"judul":"panasonic microwave oven parts","link":"http:\/\/c.searspartsdirect.com\/lis_png\/PLDM\/P0912074-00001.png","thumb":"https:\/\/tse2.mm.bing.net\/th?id=OIP.6hVM4eKd5hE9JFwhFObNmAHaFt&pid=Api&P=0&w=300&h=300"},{"judul":"panasonic microwave parts","link":"http:\/\/c.searspartsdirect.com\/lis_png\/PLDM\/50021237-00001.png","thumb":"https:\/\/tse4.mm.bing.net\/th?id=OIP.8Onj7rm78zHypg9dlFranQHaFa&pid=Api&P=0&w=300&h=300"},{"judul":"panasonic panasonic microwave oven parts","link":"http:\/\/c.searspartsdirect.com\/lis_png\/PLDM\/50020283-00001.png","thumb":"https:\/\/tse3.mm.bing.net\/th?id=OIP.uCDtPLlICO_zWYgn8ms9RwHaFj&pid=Api&P=0&w=300&h=300"},{"judul":"panasonic microwave parts","link":"http:\/\/c.searspartsdirect.com\/lis_png\/PLDM_DIR_250x250\/5002\/50021585-00001.png","thumb":"https:\/\/tse3.mm.bing.net\/th?id=OIP.H5hiqOaT1v4O_78sIrs5FwHaFU&pid=Api&P=0&w=300&h=300"},{"judul":"panasonic inverter microwave parts diagram","link":"https:\/\/c.searspartsdirect.com\/lis_png\/PLDM\/10042390-00001.png","thumb":"https:\/\/tse3.mm.bing.net\/th?id=OIP.LAaYBszCUt4RhWKHLlhSLQHaEr&pid=Api&P=0&w=300&h=300"},{"judul":"sharp microwave parts","link":"http:\/\/c.searspartsdirect.com\/lis_png\/PLDM\/P0101141-00001.png","thumb":"https:\/\/tse2.mm.bing.net\/th?id=OIP.CuWhRZotpAlU2kQKVmfIuQHaJm&pid=Api&P=0&w=300&h=300"},{"judul":"microwave oven page 2 diagram  u0026 parts list for model","link":"http:\/\/c.searspartsdirect.com\/lis_png\/PLDM\/WA001767-00002.png","thumb":"https:\/\/tse1.mm.bing.net\/th?id=OIP.uOV_enwhTJ2T_3tFw3eN1wHaLc&pid=Api&P=0&w=300&h=300"},{"judul":"panasonic microwave parts manual  u2013 bestmicrowave","link":"http:\/\/pdfasset.owneriq.net\/e\/db\/edbe382e-b592-4e8c-b4ae-54447857b6b6\/edbe382e-b592-4e8c-b4ae-54447857b6b6-bg2.png","thumb":"https:\/\/tse2.mm.bing.net\/th?id=OIP.zbyNgy6vGk2aHQ9H_fAGUQHaKX&pid=Api&P=0&w=300&h=300"},{"judul":"panasonic panasonic microwave oven parts","link":"https:\/\/c.searspartsdirect.com\/lis_png\/PLDM\/50020011-00002.png","thumb":"https:\/\/tse2.mm.bing.net\/th?id=OIP.gzvw5vTTAMNTCpbAQ4xIiwHaFI&pid=Api&P=0&w=300&h=300"},{"judul":"panasonic panasonic microwave oven parts","link":"https:\/\/c.searspartsdirect.com\/lis_png\/PLDM\/50020011-00003.png","thumb":"https:\/\/tse1.mm.bing.net\/th?id=OIP.38z-ENOY92OlvIjMiJlS_wHaFx&pid=Api&P=0&w=300&h=300"},{"judul":"panasonic panasonic microwave oven parts","link":"https:\/\/c.searspartsdirect.com\/lis_png\/PLDM\/50020011-00004.png","thumb":"https:\/\/tse4.mm.bing.net\/th?id=OIP.X8oI4kXEenXmqvAEjBblIgHaD5&pid=Api&P=0&w=300&h=300"},{"judul":"301 moved permanently","link":"http:\/\/c.searspartsdirect.com\/lis_png\/PLDM\/50020010-00004.png","thumb":"https:\/\/tse4.mm.bing.net\/th?id=OIP.qOiniHcBdg61GHk0qL_eZgHaFu&pid=Api&P=0&w=300&h=300"},{"judul":"301 moved permanently","link":"http:\/\/c.searspartsdirect.com\/lis_png\/PLDM\/50022183-00005.png","thumb":"https:\/\/tse1.mm.bing.net\/th?id=OIP.XXXwYDsdnNrbmvwtFT91LgHaE0&pid=Api&P=0&w=300&h=300"},{"judul":"301 moved permanently","link":"http:\/\/c.searspartsdirect.com\/lis_png\/PLDM\/50020010-00005.png","thumb":"https:\/\/tse1.mm.bing.net\/th?id=OIP.NGmBNFKmtrwbPLgL-hfCRQHaEc&pid=Api&P=0&w=300&h=300"},{"judul":"microwave parts listbestmicrowave","link":"https:\/\/cdn.appliancefactoryparts.com\/images\/breakdowns\/1000\/148785-1.gif","thumb":"https:\/\/tse4.mm.bing.net\/th?id=OIP.x7186RMDynC-pirKoWm-kwHaF6&pid=Api&P=0&w=300&h=300"},{"judul":"cabinet and door diagram  u0026 parts list for model mw8650xs7","link":"http:\/\/c.searspartsdirect.com\/lis_png\/PLDM\/O2010120-00004.png","thumb":"https:\/\/tse2.mm.bing.net\/th?id=OIP.ipzNk7nhPvRj_sAid-9BZAHaJV&pid=Api&P=0&w=300&h=300"},{"judul":"complete microwave page 2 diagram  u0026 parts list for model","link":"http:\/\/c.searspartsdirect.com\/lis_png\/PLDM\/WA001784-00033.png","thumb":"https:\/\/tse4.mm.bing.net\/th?id=OIP.xzimzXS8-vAR14lJsRyrIQHaJl&pid=Api&P=0&w=300&h=300"},{"judul":"panasonic microwave parts manual  u2013 bestmicrowave","link":"https:\/\/cdn.appliancefactoryparts.com\/images\/breakdowns\/1000\/148794-1.gif","thumb":"https:\/\/tse3.mm.bing.net\/th?id=OIP.9vO7K9Z1DqM_dKusqXHzrQHaHS&pid=Api&P=0&w=300&h=300"},{"judul":"panasonic microwave oven wiring material parts","link":"http:\/\/c.searspartsdirect.com\/lis_png\/PLDM\/50022181-00004.png","thumb":"https:\/\/tse4.mm.bing.net\/th?id=OIP.yyK2p0GfCz1wEiuiBtozWAHaFt&pid=Api&P=0&w=300&h=300"},{"judul":"schematic diagram  aph  diagram  u0026 parts list for model","link":"http:\/\/c.searspartsdirect.com\/lis_png\/PLDM\/P0104055-00005.png","thumb":"https:\/\/tse4.mm.bing.net\/th?id=OIP.PrkXrnrPem6WUlftGBpC-gHaJm&pid=Api&P=0&w=300&h=300"},{"judul":"complete microwave assembly page 2 diagram  u0026 parts list","link":"http:\/\/c.searspartsdirect.com\/lis_png\/PLDM\/WA001782-00002.png","thumb":"https:\/\/tse3.mm.bing.net\/th?id=OIP.ir5mGoCQXpBPUqnEseQjGwHaJl&pid=Api&P=0&w=300&h=300"},{"judul":"panasonic microwave parts manual  u2013 bestmicrowave","link":"https:\/\/cdn.appliancefactoryparts.com\/images\/breakdowns\/1000\/147896-1.gif","thumb":"https:\/\/tse2.mm.bing.net\/th?id=OIP.9ej_wzC4hbqgIIO_mMXOXwHaCh&pid=Api&P=0&w=300&h=300"},{"judul":"panasonic nn","link":"https:\/\/c.searspartsdirect.com\/lis_png\/PLDM\/50019470-00002.png?wid=150u0026hei=150u0026resMode=sharp","thumb":"https:\/\/tse3.mm.bing.net\/th?id=OIP.4lobBE8XdJP0E3VNwzG9fgHaFQ&pid=Api&P=0&w=300&h=300"},{"judul":"complete microwave page 2 diagram  u0026 parts list for model","link":"http:\/\/c.searspartsdirect.com\/lis_png\/PLDM\/WA001800-00026.png","thumb":"https:\/\/tse1.mm.bing.net\/th?id=OIP.w648wOInsSei1-oyfTqYlAHaJl&pid=Api&P=0&w=300&h=300"},{"judul":"exploded view  parts list diagram  u0026 parts list for model","link":"http:\/\/c.searspartsdirect.com\/lis_png\/PLDM\/WA001798-00026.png","thumb":"https:\/\/tse1.mm.bing.net\/th?id=OIP._vojWZ-HK6HFv7C2feEX3QHaJl&pid=Api&P=0&w=300&h=300"},{"judul":"complete microwave oven page 2 diagram  u0026 parts list for","link":"http:\/\/c.searspartsdirect.com\/lis_png\/PLDM\/WA001803-00025.png","thumb":"https:\/\/tse4.mm.bing.net\/th?id=OIP._E-8PS69JbUa-lzUKkXC9AHaJl&pid=Api&P=0&w=300&h=300"},{"judul":"door  outer cabinet diagram  u0026 parts list for model","link":"http:\/\/c.searspartsdirect.com\/lis_png\/PLDM\/I2200550-00003.png","thumb":"https:\/\/tse2.mm.bing.net\/th?id=OIP.LJZOtEMSrkFPYfyDqxCe5gHaJh&pid=Api&P=0&w=300&h=300"},{"judul":"exploded view and parts list diagram  u0026 parts list for","link":"http:\/\/c.searspartsdirect.com\/lis_png\/PLDM\/WA001795-00020.png","thumb":"https:\/\/tse1.mm.bing.net\/th?id=OIP.rUqjdiCCD7ai6Yjsihg6_AHaLc&pid=Api&P=0&w=300&h=300"},{"judul":"cabinet parts diagram  u0026 parts list for model mw8985s","link":"http:\/\/c.searspartsdirect.com\/lis_png\/PLDM\/50020455-00003.png","thumb":"https:\/\/tse2.mm.bing.net\/th?id=OIP.rXOqM3iXCDKpWxJiU_d4IQHaId&pid=Api&P=0&w=300&h=300"},{"judul":"panasonic nn","link":"https:\/\/c.searspartsdirect.com\/lis_png\/PLDM\/50020165-00001.png?wid=150u0026hei=150u0026resMode=sharp","thumb":"https:\/\/tse3.mm.bing.net\/th?id=OIP.DvJWKCWG4RsMW5dU34cqOgHaFv&pid=Api&P=0&w=300&h=300"},{"judul":"looking for panasonic model nn","link":"https:\/\/c.searspartsdirect.com\/lis_png\/PLDM\/50041921-00003.png?wid=150u0026hei=150","thumb":"https:\/\/tse2.mm.bing.net\/th?id=OIP.BpIMYrrqw9tHaAAe8ZDoNAHaGM&pid=Api&P=0&w=300&h=300"},{"judul":"looking for panasonic model nn","link":"https:\/\/c.searspartsdirect.com\/lis_png\/PLDM\/50041921-00002.png?wid=150u0026hei=150u0026resMode=sharp","thumb":"https:\/\/tse2.mm.bing.net\/th?id=OIP.ABFvXjjXOq11oFdn1sBHzAHaG0&pid=Api&P=0&w=300&h=300"},{"judul":"complete microwave assembly diagram  u0026 parts list for model","link":"http:\/\/c.searspartsdirect.com\/lis_png\/PLDM\/WA001375-00025.png","thumb":"https:\/\/tse3.mm.bing.net\/th?id=OIP._SMBDdJqNcgY3GsHRQLJXgHaLc&pid=Api&P=0&w=300&h=300"},{"judul":"cabinet and stirrer parts diagram  u0026 parts list for model","link":"http:\/\/c.searspartsdirect.com\/lis_png\/PLDM\/W0708170-00004.png","thumb":"https:\/\/tse1.mm.bing.net\/th?id=OIP.gbmElBvTV-kkpOnX96cpggHaKO&pid=Api&P=0&w=300&h=300"},{"judul":"panasonic microwave parts","link":"http:\/\/c.searspartsdirect.com\/lis_png\/PLDM_DIR_250x250\/5003\/50036269-00003.png","thumb":"https:\/\/tse2.mm.bing.net\/th?id=OIP.1L9Udaa8MN7iMk7OvsVM3QHaEw&pid=Api&P=0&w=300&h=300"},{"judul":"panasonic nn","link":"https:\/\/c.searspartsdirect.com\/lis_png\/PLDM\/50034948-00004.png?wid=150u0026hei=150u0026resMode=sharp","thumb":"https:\/\/tse3.mm.bing.net\/th?id=OIP.4JQn6K8QTcdGcyGSNcJ0DQHaFZ&pid=Api&P=0&w=300&h=300"},{"judul":"exploded view  parts list diagram  u0026 parts list for model","link":"http:\/\/c.searspartsdirect.com\/lis_png\/PLDM\/WA001798-00024.png","thumb":"https:\/\/tse1.mm.bing.net\/th?id=OIP.361916TRV6PhERyzGm4mAgHaJl&pid=Api&P=0&w=300&h=300"},{"judul":"looking for panasonic model nn","link":"https:\/\/c.searspartsdirect.com\/lis_png\/PLDM\/50036252-00001.png?wid=150u0026hei=150u0026resMode=sharp","thumb":"https:\/\/tse4.mm.bing.net\/th?id=OIP.0GmveFVxYPeCwviJ_oG0UAHaFc&pid=Api&P=0&w=300&h=300"},{"judul":"cabinet parts diagram  u0026 parts list for model kb6014lk","link":"http:\/\/c.searspartsdirect.com\/lis_png\/PLDM\/50029876-00003.png","thumb":"https:\/\/tse2.mm.bing.net\/th?id=OIP.6nFkl1Guhxg3GNvlw_Ug6gHaJl&pid=Api&P=0&w=300&h=300"},{"judul":"panasonic microwave parts","link":"http:\/\/c.searspartsdirect.com\/lis_png\/PLDM_DIR_250x250\/5003\/50036252-00003.png","thumb":"https:\/\/tse1.mm.bing.net\/th?id=OIP.DYExu7v_iLYFyWvafEV77gHaEp&pid=Api&P=0&w=300&h=300"},{"judul":"complete microwave oven page 2 diagram  u0026 parts list for","link":"http:\/\/c.searspartsdirect.com\/lis_png\/PLDM\/WA001776-00066.png","thumb":"https:\/\/tse2.mm.bing.net\/th?id=OIP.EGsxmrMmzu0qmiuByxYoRwHaLc&pid=Api&P=0&w=300&h=300"},{"judul":"complete microwave oven diagram  u0026 parts list for model","link":"http:\/\/c.searspartsdirect.com\/lis_png\/PLDM\/WA001776-00065.png","thumb":"https:\/\/tse3.mm.bing.net\/th?id=OIP.Dffxjz4J3AgdWT6Wry_FpwHaLc&pid=Api&P=0&w=300&h=300"},{"judul":"301 moved permanently","link":"http:\/\/c.searspartsdirect.com\/lis_png\/PLDM\/WA001768-00015.png","thumb":"https:\/\/tse1.mm.bing.net\/th?id=OIP.V22JVU5WO4K-J6M3tiv6_AHaJl&pid=Api&P=0&w=300&h=300"},{"judul":"cabinet diagram  u0026 parts list for model mh6700xw0 whirlpool","link":"http:\/\/c.searspartsdirect.com\/lis_png\/PLDM\/O2004304-00004.png","thumb":"https:\/\/tse3.mm.bing.net\/th?id=OIP.iPDB5CTo4T71pY4X6Y1aQQHaJY&pid=Api&P=0&w=300&h=300"},{"judul":"sharp microwave parts","link":"http:\/\/c.searspartsdirect.com\/lis_png\/PLDM\/50034077-00001.png","thumb":"https:\/\/tse2.mm.bing.net\/th?id=OIP.IHWz0ifsmJ2WbywYXKuXRwHaJ6&pid=Api&P=0&w=300&h=300"},{"judul":"full size","link":"http:\/\/c.searspartsdirect.com\/lis_png\/PLDM\/WA001492-00014.png","thumb":"https:\/\/tse4.mm.bing.net\/th?id=OIP.8qCXEwYRU61i18LVT3bFwAHaJl&pid=Api&P=0&w=300&h=300"},{"judul":"301 moved permanently","link":"http:\/\/c.searspartsdirect.com\/lis_png\/PLDM\/I2200118-00005.png","thumb":"https:\/\/tse3.mm.bing.net\/th?id=OIP.txUqfieZn6yjkAZU739XsAHaJV&pid=Api&P=0&w=300&h=300"},{"judul":"cabinet diagram  u0026 parts list for model mh6110xeb1","link":"http:\/\/c.searspartsdirect.com\/lis_png\/PLDM\/O2027043-00003.png","thumb":"https:\/\/tse1.mm.bing.net\/th?id=OIP.zMADTHvVCM2yYlA8iCk9OwHaHL&pid=Api&P=0&w=300&h=300"},{"judul":"301 moved permanently","link":"http:\/\/c.searspartsdirect.com\/lis_png\/PLDM\/WA001798-00005.png","thumb":"https:\/\/tse2.mm.bing.net\/th?id=OIP.-9S5cS-9LoiNqRIXYLl39gHaJl&pid=Api&P=0&w=300&h=300"}]