[{"judul":"kenwood kdc car stereo wiring diagram","link":"https:\/\/static-assets.imageservice.cloud\/1460025\/kdc-mp145-wiring-diagram-wiring-diagram.png","thumb":"https:\/\/tse1.mm.bing.net\/th?id=OIP.OHuPeK69YfSs6gK6afDzWQHaKc&pid=Api&P=0&w=300&h=300"},{"judul":"kenwood kdc 132 wiring diagram","link":"https:\/\/schematron.org\/image\/kenwood-kdc-132-wiring-diagram-4.png","thumb":"https:\/\/tse2.mm.bing.net\/th?id=OIP.P5eJYhe-Ef02ibB6QJ_DHQHaJl&pid=Api&P=0&w=300&h=300"},{"judul":"kenwood kdc 138 wiring diagram","link":"http:\/\/schematron.org\/image\/kenwood-kdc-138-wiring-diagram-8.png","thumb":"https:\/\/tse4.mm.bing.net\/th?id=OIP.JjJMFDAqOqWCDLlMOoiJxwHaJl&pid=Api&P=0&w=300&h=300"},{"judul":"what colour is the remote wire on a kenwood kdc","link":"https:\/\/ww2.justanswer.com\/uploads\/Benimur\/2012-07-09_110252_kenwood_kdc-x789_wiring_diagram.jpg","thumb":"https:\/\/tse3.mm.bing.net\/th?id=OIP.cD3wdPSdaZqos-hULhKPaQHaHV&pid=Api&P=0&w=300&h=300"},{"judul":"kenwood kdc u456 wiring diagram","link":"http:\/\/schematron.org\/image\/kenwood-kdc-u456-wiring-diagram-7.png","thumb":"https:\/\/tse2.mm.bing.net\/th?id=OIP.5N4TPEAkUJYDPQNQJ7RK3AHaJl&pid=Api&P=0&w=300&h=300"},{"judul":"kenwood kdc","link":"https:\/\/schematron.org\/image\/kenwood-kdc-mp438u-wiring-diagram.jpg","thumb":"https:\/\/tse3.mm.bing.net\/th?id=OIP.qir_qNqb2UMVSiH7PNsLzgHaKf&pid=Api&P=0&w=300&h=300"},{"judul":"kenwood kdc x502 wiring diagram","link":"https:\/\/schematron.org\/image\/kenwood-kdc-x502-wiring-diagram-8.png","thumb":"https:\/\/tse3.mm.bing.net\/th?id=OIP.vDVG-WKqd3Q7SC73fifxyAHaKe&pid=Api&P=0&w=300&h=300"},{"judul":"kenwood kdc","link":"http:\/\/schematron.org\/image\/kenwood-kdc-mp438u-wiring-diagram-7.jpg","thumb":"https:\/\/tse3.explicit.bing.net\/th?id=OIP.-nr2MO6NKHM_mxHozse9qQHaKg&pid=Api&P=0&w=300&h=300"},{"judul":"connecting wires to terminals","link":"https:\/\/annawiringdiagram.com\/wp-content\/uploads\/2019\/02\/kenwood-kdc-108-wiring-diagram-best-of-2019-software-equation-kenwood-kdc-wiring-diagram.jpg","thumb":"https:\/\/tse3.mm.bing.net\/th?id=OIP.GpV_Pq9Ydp8IVounBLfNdwHaJ2&pid=Api&P=0&w=300&h=300"},{"judul":"kenwood kdc hd455u wiring diagram","link":"https:\/\/wiringall.com\/image\/kenwood-kdc-hd455u-wiring-diagram-4.jpg","thumb":"https:\/\/tse1.mm.bing.net\/th?id=OIP._6IIapRl7tcGb3svXAG94gHaN0&pid=Api&P=0&w=300&h=300"},{"judul":"my kenwood kdc","link":"http:\/\/ww2.justanswer.com\/uploads\/MO\/molurch\/2013-02-06_193326_13.png","thumb":"https:\/\/tse1.mm.bing.net\/th?id=OIP.cMigpC9lZQ4Ac280JgZSSAHaJr&pid=Api&P=0&w=300&h=300"},{"judul":"kenwood kdc","link":"https:\/\/wiringall.com\/image\/kenwood-kdc-210u-wiring-diagram.gif","thumb":"https:\/\/tse1.mm.bing.net\/th?id=OIP.tQNXSBnoGBIfH2375Wiz3gHaKP&pid=Api&P=0&w=300&h=300"},{"judul":"kenwood kdc 252u wiring diagram","link":"https:\/\/diagramweb.net\/img\/kenwood-kdc-252u-wiring-diagram-3.png","thumb":"https:\/\/tse2.mm.bing.net\/th?id=OIP.F_omwmi0X_xZkw-V3gSUCwHaJl&pid=Api&P=0&w=300&h=300"},{"judul":"kenwood excelon kdc x395 wiring diagram","link":"https:\/\/diagramweb.net\/img\/kenwood-kdc-x395-wiring-diagram-10.jpg","thumb":"https:\/\/tse2.mm.bing.net\/th?id=OIP.xGQuTPkO4cnOl_b4PowcXQHaJl&pid=Api&P=0&w=300&h=300"},{"judul":"kenwood kdc 255u wiring diagram","link":"https:\/\/diagramweb.net\/img\/kenwood-kdc-255u-wiring-diagram-2.png","thumb":"https:\/\/tse3.mm.bing.net\/th?id=OIP.GXzqbK6mYiaQRNk9QWoBYQHaJl&pid=Api&P=0&w=300&h=300"},{"judul":"kenwood kdc bt852hd wiring diagram","link":"http:\/\/schematron.org\/image\/kenwood-kdc-bt852hd-wiring-diagram-7.jpg","thumb":"https:\/\/tse1.mm.bing.net\/th?id=OIP.1EUdHC6SlHiAUOJNt-dXLwHaK_&pid=Api&P=0&w=300&h=300"},{"judul":"kenwood kdc 516s wiring diagram","link":"https:\/\/schematron.org\/image\/kenwood-kdc-516s-wiring-diagram-6.png","thumb":"https:\/\/tse2.mm.bing.net\/th?id=OIP.26uE4f7vmuvdNQNJ9tG0MgHaJl&pid=Api&P=0&w=300&h=300"},{"judul":"kenwood kdc 355u wiring diagram","link":"https:\/\/schematron.org\/image\/kenwood-kdc-355u-wiring-diagram-3.png","thumb":"https:\/\/tse1.mm.bing.net\/th?id=OIP.XwHJJ5zsuxBsvo5yy16vbQHaJl&pid=Api&P=0&w=300&h=300"},{"judul":"wiring diagram kenwood kdc mp345u","link":"https:\/\/diagramweb.net\/img\/wiring-diagram-kenwood-kdc-mp345u-5.jpg","thumb":"https:\/\/tse2.mm.bing.net\/th?id=OIP.welCe7IzG0qNV_j0vYHm8gHaIO&pid=Api&P=0&w=300&h=300"},{"judul":"kenwood kdc","link":"https:\/\/schematron.org\/image\/kenwood-kdc-bt318u-wiring-diagram-5.png","thumb":"https:\/\/tse4.mm.bing.net\/th?id=OIP.-2sMcpkHeTt5j7w2cviq_QHaJl&pid=Api&P=0&w=300&h=300"},{"judul":"kenwood kdc 2019 wiring diagram","link":"http:\/\/schematron.org\/image\/kenwood-kdc-2019-wiring-diagram-7.jpg","thumb":"https:\/\/tse1.mm.bing.net\/th?id=OIP.HTPXEkWF9JeLqejoVdBADQHaKf&pid=Api&P=0&w=300&h=300"},{"judul":"kenwood kdc mp342u wiring diagram","link":"https:\/\/schematron.org\/image\/kenwood-kdc-mp342u-wiring-diagram-11.png","thumb":"https:\/\/tse1.mm.bing.net\/th?id=OIP.OmawokL6BY_hC299BB94ngHaKA&pid=Api&P=0&w=300&h=300"},{"judul":"kenwood kdc","link":"http:\/\/schematron.org\/image\/kenwood-kdc-bt318u-wiring-diagram-10.png","thumb":"https:\/\/tse4.mm.bing.net\/th?id=OIP.NrWSMF72y_ZetJETLDaQ1gHaJl&pid=Api&P=0&w=300&h=300"},{"judul":"kenwood kdc 222 wiring diagram","link":"https:\/\/schematron.org\/image\/kenwood-kdc-222-wiring-diagram-2.png","thumb":"https:\/\/tse2.mm.bing.net\/th?id=OIP.e1hFcUhxiDt4d1FtHYq1JQHaJl&pid=Api&P=0&w=300&h=300"},{"judul":"kenwood kdc 108 wiring diagram","link":"https:\/\/elektrotanya.com\/PREVIEWS\/39485642\/23432455\/kenwood\/kenwood_kdc-108_kdc-148_kdc-3051m__kdc-315m_kdc-mp1049_kdc-mp148cr_kdc-mp149_kdc-mp2049_kdc-mp249_kdc-mp3049.pdf_2.png","thumb":"https:\/\/tse1.mm.bing.net\/th?id=OIP.t1529cZmj3RcjaGlPRaDQAHaFu&pid=Api&P=0&w=300&h=300"},{"judul":"kenwood kdc u456 wiring diagram","link":"https:\/\/schematron.org\/image\/kenwood-kdc-u456-wiring-diagram-2.jpg","thumb":"https:\/\/tse1.mm.bing.net\/th?id=OIP.yBUcKiSB0mlfzYrO2KZo8gHaHa&pid=Api&P=0&w=300&h=300"},{"judul":"kenwood kdc 252u wiring diagram","link":"https:\/\/diagramweb.net\/img\/kenwood-kdc-252u-wiring-diagram-5.jpeg","thumb":"https:\/\/tse4.mm.bing.net\/th?id=OIP.oI-r2OJnIBrM0voFknbn0AHaKd&pid=Api&P=0&w=300&h=300"},{"judul":"kenwood kdc 352u wiring diagram","link":"https:\/\/schematron.org\/image\/kenwood-kdc-352u-wiring-diagram-7.png","thumb":"https:\/\/tse2.mm.bing.net\/th?id=OIP.14USNqfVXtLCWEbnEr_BdwHaFP&pid=Api&P=0&w=300&h=300"},{"judul":"kenwood kdc","link":"http:\/\/schematron.org\/image\/kenwood-kdc-bt318u-wiring-diagram-4.png","thumb":"https:\/\/tse3.mm.bing.net\/th?id=OIP.j-NloBQ2AHhR_E2d7gqDewHaJl&pid=Api&P=0&w=300&h=300"},{"judul":"30 kenwood kvt 512 wiring diagram","link":"https:\/\/elektrotanya.com\/PREVIEWS\/39485642\/service-tips-info\/kenwood\/kenwood_kdc-215s-2011s-315s-3005-3011-415s-4005-4007-4009-4011s-4015-515s-5001-5003-5005-5007-5011-6001-6003-6005-6007-6009-6015-x615-715s-7000_csn-0150_info.pdf_1.png","thumb":"https:\/\/tse3.mm.bing.net\/th?id=OIP.9qOToNgeNZGvvBqgJ-R5kwHaJl&pid=Api&P=0&w=300&h=300"},{"judul":"kenwood kdc","link":"https:\/\/ricardolevinsmorales.com\/wp-content\/uploads\/2018\/09\/kenwood-kdc-210u-wiring-diagram-wiring-diagram-kenwood-stereo-top-rated-kenwood-wiring-harness-wires-fixya-wire-center-e280a2-5s.jpg","thumb":"https:\/\/tse2.mm.bing.net\/th?id=OIP.xc09bYehelEVCzbZkO1fyQHaFj&pid=Api&P=0&w=300&h=300"},{"judul":"35 kenwood kdc 255u wiring diagram","link":"http:\/\/eyelash.me\/wp-content\/uploads\/with-kenwood-kdc-138-wiring-diagram.gif","thumb":"https:\/\/tse1.mm.bing.net\/th?id=OIP.w7Y7A63lodmUUjJ8w3fS6wHaF7&pid=Api&P=0&w=300&h=300"},{"judul":"kenwood kdc","link":"http:\/\/schematron.org\/image\/kenwood-kdc-152-wiring-diagram-7.jpg","thumb":"https:\/\/tse2.mm.bing.net\/th?id=OIP.Tn4MRNissSD6VJFQNWN2cgHaJQ&pid=Api&P=0&w=300&h=300"},{"judul":"33 kenwood kdc 108 wiring diagram","link":"http:\/\/mainetreasurechest.com\/wp-content\/uploads\/2018\/06\/kenwood-kdc-108-wiring-diagram-elegant-enchanting-kdc-x498-wiring-harness-diagram-model-electrical-of-kenwood-kdc-108-wiring-diagram.jpg","thumb":"https:\/\/tse2.mm.bing.net\/th?id=OIP.evvmxaENFm70_lxcKkYlcQHaJS&pid=Api&P=0&w=300&h=300"},{"judul":"kenwood car cd player wiring diagram","link":"https:\/\/static-assets.imageservice.cloud\/10577167\/kenwood-wiring-diagram-malochicolovecom.jpg","thumb":"https:\/\/tse3.mm.bing.net\/th?id=OIP.upFd6cfNOxKaiauu8oZwHQHaFs&pid=Api&P=0&w=300&h=300"},{"judul":"kenwood excelon kdc x395 wiring diagram","link":"https:\/\/www.tankbig.com\/wp-content\/uploads\/2019\/02\/kenwood_kdc_x395_wiring_diagram_radio_awesome_magnificent_head_unit_4.jpg","thumb":"https:\/\/tse2.mm.bing.net\/th?id=OIP.hyI2PEaOa8fzh4Akl-n2eQHaF7&pid=Api&P=0&w=300&h=300"},{"judul":"kdc bt762hd wiring diagram","link":"https:\/\/wiringall.com\/image\/kdc-bt762hd-wiring-diagram-5.jpg","thumb":"https:\/\/tse1.mm.bing.net\/th?id=OIP.hw4DxscFgH9WfqZKv5yvKAHaKf&pid=Api&P=0&w=300&h=300"},{"judul":"kenwood kdc 210u wiring diagram","link":"http:\/\/schematron.org\/image\/kenwood-kdc-210u-wiring-diagram-8.png","thumb":"https:\/\/tse2.mm.bing.net\/th?id=OIP.awO1MNXB8MTcYC9lMGR03AHaJl&pid=Api&P=0&w=300&h=300"},{"judul":"kenwood kdc-mp342u wiring diagram","link":"https:\/\/tops-stars.com\/wp-content\/uploads\/2017\/09\/kenwood-wiring-schematics-kenwood-car-stereo-wiring-harness-wiring-within-kenwood-kdc-mp342u-wiring-diagram.jpg","thumb":"https:\/\/tse1.mm.bing.net\/th?id=OIP.qTTKk9sFYAxmm94O9TWrDAHaGt&pid=Api&P=0&w=300&h=300"},{"judul":"kdc 152 wiring diagram","link":"https:\/\/www.chanish.org\/wp-content\/uploads\/2019\/01\/kenwood_kdc_152_wiring_diagram_0.jpg","thumb":"https:\/\/tse4.mm.bing.net\/th?id=OIP.eE_ih-PEPbQISCgn4zEJDwAAAA&pid=Api&P=0&w=300&h=300"},{"judul":"wiring diagram kenwood dnx574s","link":"https:\/\/diagramweb.net\/img\/wiring-diagram-kenwood-dnx574s-6.png","thumb":"https:\/\/tse2.mm.bing.net\/th?id=OIP.m0KAH5VTn07oQyZDeQywMAHaJl&pid=Api&P=0&w=300&h=300"},{"judul":"kenwood kdc","link":"https:\/\/diagramweb.net\/img\/kenwood-kdc-hd548u-wiring-diagram-10.png","thumb":"https:\/\/tse3.mm.bing.net\/th?id=OIP.arhLtY1emr_unSOWuJm_mgHaJl&pid=Api&P=0&w=300&h=300"},{"judul":"kenwood kdc","link":"https:\/\/schematron.org\/image\/kenwood-kdc-x895-plug-wiring-diagram.png","thumb":"https:\/\/tse1.mm.bing.net\/th?id=OIP.08Zskl06N-h0B5DEXb212wHaJl&pid=Api&P=0&w=300&h=300"},{"judul":"kenwood kdc","link":"https:\/\/wiringall.com\/image\/kenwood-kdc-x895-wiring-diagram-2.png","thumb":"https:\/\/tse2.mm.bing.net\/th?id=OIP.-7gVf6d0J9M5lNnZ_SqYmQHaKi&pid=Api&P=0&w=300&h=300"},{"judul":"kenwood kdc mp638u wiring diagram","link":"https:\/\/diagramweb.net\/img\/kenwood-kdc-mp638u-wiring-diagram.jpg","thumb":"https:\/\/tse4.mm.bing.net\/th?id=OIP.w47IraN6EdEQX_XUuNUM4wHaHa&pid=Api&P=0&w=300&h=300"},{"judul":"kenwood kdc bt648u wiring diagram","link":"https:\/\/diagramweb.net\/img\/kenwood-kdc-bt648u-wiring-diagram.jpg","thumb":"https:\/\/tse3.mm.bing.net\/th?id=OIP.iAgFNhwhS983AkbqVaOVjAHaGC&pid=Api&P=0&w=300&h=300"},{"judul":"kenwood kdc","link":"https:\/\/diagramweb.net\/img\/kenwood-kdc-mp142-cd-receiver-wiring-diagram-10.png","thumb":"https:\/\/tse2.mm.bing.net\/th?id=OIP.36sLoW3oAuO_0iG34Qf6JAHaKV&pid=Api&P=0&w=300&h=300"},{"judul":"kenwood kdc mp238 wiring diagram","link":"https:\/\/www.chanish.org\/wp-content\/uploads\/2019\/03\/kenwood_kdc_mp238_wiring_diagram_3.jpg","thumb":"https:\/\/tse3.mm.bing.net\/th?id=OIP.ivX1OoTEx9OvzlFgocK3nAHaEu&pid=Api&P=0&w=300&h=300"},{"judul":"kenwood kdc 138 wiring harness diagram","link":"https:\/\/wiringall.com\/image\/kenwood-kdc-138-wiring-harness-diagram-8.jpg","thumb":"https:\/\/tse4.mm.bing.net\/th?id=OIP.5iAGzJ_GHyUwARGNbZg9rAHaO7&pid=Api&P=0&w=300&h=300"},{"judul":"kenwood kdc 352u wiring diagram","link":"https:\/\/schematron.org\/image\/kenwood-kdc-352u-wiring-diagram-8.png","thumb":"https:\/\/tse1.mm.bing.net\/th?id=OIP.-E6LLgHZK9J7txJJI4H2SAHaKe&pid=Api&P=0&w=300&h=300"},{"judul":"kenwood kdc","link":"https:\/\/annawiringdiagram.com\/wp-content\/uploads\/2019\/02\/wire-diagram-kenwood-kdc-210u-manual-e-books-kenwood-kdc-210u-wiring-diagram.png","thumb":"https:\/\/tse2.mm.bing.net\/th?id=OIP.StPVhf5hDlNGJFaWBP8wNwHaH3&pid=Api&P=0&w=300&h=300"},{"judul":"kenwood kdc 222 wiring diagram","link":"https:\/\/schematron.org\/image\/kenwood-kdc-222-wiring-diagram-4.png","thumb":"https:\/\/tse4.mm.bing.net\/th?id=OIP.y3izls3IBnaT-OWUoQ6pBAHaJl&pid=Api&P=0&w=300&h=300"},{"judul":"wiring 16pin kenwood kdc 248u wiring harness diagram full","link":"https:\/\/i.pinimg.com\/originals\/b5\/29\/f3\/b529f334f94223cddaa43eff58fa845d.jpg","thumb":"https:\/\/tse4.mm.bing.net\/th?id=OIP.bLc3k6hLZgCYrq-3XKAShAHaKX&pid=Api&P=0&w=300&h=300"},{"judul":"kenwood kdc bt648u wiring diagram","link":"https:\/\/diagramweb.net\/img\/kenwood-kdc-bt648u-wiring-diagram-4.png","thumb":"https:\/\/tse1.mm.bing.net\/th?id=OIP.JlhkM36SPxyKf2LPX0mXUAHaFB&pid=Api&P=0&w=300&h=300"}]