[{"judul":"index of   schema  scooter  peugeot","link":"http:\/\/motelek.net\/schema\/scooter\/peugeot\/elystar125.png","thumb":"https:\/\/tse1.mm.bing.net\/th?id=OIP.zzDs4vopGnQHvzHag9YHVQHaFj&pid=Api&P=0&w=300&h=300"},{"judul":"peugeot wiring diagrams","link":"https:\/\/www.mopedarmy.com\/w\/images\/a\/a0\/Peugeot_102_wiring_1.png","thumb":"https:\/\/tse3.mm.bing.net\/th?id=OIP.MoFs8Y6Waq_-zc5JsxpG8QHaFa&pid=Api&P=0&w=300&h=300"},{"judul":"manuals and documents","link":"http:\/\/www.49ccscoot.com\/pics\/Wiring%20Diagrams\/Peugeot_Speedfight_ACI_100.png","thumb":"https:\/\/tse3.mm.bing.net\/th?id=OIP.JrxiJL3jUrbawE0lyVLspgHaFj&pid=Api&P=0&w=300&h=300"},{"judul":"peugeot 306 wiring diagram","link":"https:\/\/image.winudf.com\/v2\/image\/Y29tLmFkdWhhaS5wZXVnZW90NDA3d2lyaW5nZGlhZ3JhbWZ1bGxfc2NyZWVuXzZfMTUzMTI2OTM0MV8wMzI\/screen-6.jpg?fakeurl=1u0026type=.jpg","thumb":"https:\/\/tse2.mm.bing.net\/th?id=OIP.MUP7c9TaBknY7-sjLMi41wHaFy&pid=Api&P=0&w=300&h=300"},{"judul":"peugeot speedfight not starting and no front headlights","link":"http:\/\/i905.photobucket.com\/albums\/ac258\/bashan_2010\/Electrical%20Tech%20Posts\/moto_schem_Peugeot_Speedfight_with_ACI100_ignition_scooter1.jpg","thumb":"https:\/\/tse2.mm.bing.net\/th?id=OIP.OTRTuEOH5X9oH_6qP9KClwHaFm&pid=Api&P=0&w=300&h=300"},{"judul":"peugeot 306 hdi wiring diagram","link":"https:\/\/i.pinimg.com\/originals\/ee\/47\/bd\/ee47bd2adc82acaea98750a66f776e65.jpg","thumb":"https:\/\/tse2.mm.bing.net\/th?id=OIP.CxsdhmioqQoSdWwyVuuDRQHaFm&pid=Api&P=0&w=300&h=300"},{"judul":"europa contactor wiring diagram","link":"https:\/\/www.kollmorgen.com\/sites\/default\/files\/pictures\/stopp1_e.jpg","thumb":"https:\/\/tse3.mm.bing.net\/th?id=OIP.4BvC4qGWvEKDK4xWSTT4kQHaIU&pid=Api&P=0&w=300&h=300"},{"judul":"temi per 2006 vento phantom r4i specifiche   nuovo","link":"http:\/\/img.paratamoto.com\/full\/0660d62bf03655e0.jpg","thumb":"https:\/\/tse1.mm.bing.net\/th?id=OIP.D8f48HfGL781SumvJuVzOAHaC_&pid=Api&P=0&w=300&h=300"},{"judul":"stromlaufplan peugeot 307","link":"https:\/\/i1.wp.com\/1.bp.blogspot.com\/-SkBMJio8pZg\/TeGGfWPpCBI\/AAAAAAAAAZA\/aFikqq4Kv_U\/s1600\/0009.jpg?resize%5C%5C%5C%5C%5C%5C%5C%5C%5C%5C%5C%5C%5C%5C%5C%5C%5C%5C%5C%5C%5C%5C%5C%5C%5C%5C%5C%5C%5C%5C%5C%5C%5C%5C%5C%5C%5C%5C%5C%5C%5C%5C%5C%5C%5C%5C%5C%5C%5C%5C%5C%5C%5C%5C%5C%5C%5C%5C%5C%5C%5C%5C%5C%5C%5C%5C%5C%5C%5C%5C%5C%5C%5C%5C%5C%5C%5C%5C%5C%5C%5C%5C%5C%5C%5C%5C%5C%5C%5C%5C%5C%5C%5C%5C%5C%5C%5C%5C%5C%5C%5C%5C%5C%5C%5C%5C%5C%5C%5C%5C%5C%5C%5C%5C%5C%5C%5C%5C%5C%5C%5C%5C%5C%5C%5C%5C%5C%5C%5C%5C%5C%5C%5C%5C%5C%5C%5C%5C%5C%5C%5C%5C%5C%5C%5C%5C%5C%5C%5C%5C%5C%5C%5C%5C%5C%5C%5C%5C%5C%5C%5C%5C%5C%5C%5C%5C%5C%5C%5C%5C%5C%5C%5C%5C%5C%5C%5C%5C%5C%5C%5C%5C%5C%5C%5C%5C%5C%5C%5C%5C%5C%5C%5C%5C%5C%5C%5C%5C%5C%5C%5C%5C%5C%5C%5C%5C%5C%5C%5C%5C%5C%5C%5C%5C%5C%5C%5C%5C%5C%5C%5C%5C%5C%5C%5C%5C%5C%5C%5C%5C%5C%5C%5C%5C%5C%5C%5C%5C%5C%5C%5C%5C%5C%5C%5C%5C%5C%5C%5C%5C%5C%5C%5C%5C%5C%5C%5C%5C%5C%5C%5C%5C%5C%5C%5C%5C%5C%5C%5C%5C%5C%5C%5C%5C%5C%5C%5C%5C%5C%5C%5C%5C%5C%5C%5C%5C%5C%5C%5C%5C%5C%5C%5C%5C%5C%5C%5C%5C%5C%5C%5C%5C%5C%5C%5C%5C%5C%5C%5C%5C%5C%5C%5C%5C%5C%5C%5C%5C%5C%5C%5C%5C%5C%5C%5C%5C%5C%5C%5C%5C%5C%5C%5C%5C%5C%5C%5C%5C%5C%5C%5C%5C%5C%5C%5C%5C%5C%5C%5C%5C%5C%5C%5C%5C%5C%5C%5C%5C%5C%5C%5C%5C%5C%5C%5C%5C%5C%5C%5C%5C%5C%5C%5C%5C%5C%5C%5C%5C%5C%5C%5C%5C%5C%5C%5C%5C%5C%5C%5C%5C%5C%5C%5C%5C%5C%5C%5C%5C%5C%5C%5C%5C%5C%5C%5C%5C%5C%5C%5C%5C%5C%5C%5C%5C%5C%5C%5C%5C%5C%5C%5C%5C%5C%5C%5C%5C%5C%5C%5C%5C%5C%5C%5C%5C%5C%5C%5C%5C%5C%5C%5C%5C%5C%5C%5C%5C%5C%5C%5C%5C%5C%5C%5C%5C%5C%5C%5C%5C%5C%5C%5C%5C%5C%5C%5C%5C%5C%5C%5C%5C%5C%5C%5C%5C%5C%5C%5C%5C%5C%5C%5C%5C%5C%5C%5C%5C%5C%5C%5C%5C%5C%5C%5C%5C%5C%5C%5C%5C%5C%5C%5C%5C%5C%5Cd665%2C941","thumb":"https:\/\/tse4.mm.bing.net\/th?id=OIP.0IqC-FtLNG6CR0XDiolw0AHaKe&pid=Api&P=0&w=300&h=300"},{"judul":"schaltplan peugeot speedfight 2","link":"http:\/\/img.paratamoto.com\/full\/1b22c2f66cf4a193.png","thumb":"https:\/\/tse3.mm.bing.net\/th?id=OIP.2ypAQWgcThwC0P-fAF2dkQHaFU&pid=Api&P=0&w=300&h=300"},{"judul":"documentations techniques scoot u0026 39 elec poster ici","link":"http:\/\/vehiculeselectriques.free.fr\/images\/Scooteleccablage.jpg","thumb":"https:\/\/tse4.mm.bing.net\/th?id=OIP.O-2HabYlReVROQUlmBi1dgHaC_&pid=Api&P=0&w=300&h=300"}]